queryzen/__init__.py
queryzen/backend.py
queryzen/constants.py
queryzen/exceptions.py
queryzen/queryzen.py
queryzen/sql.py
queryzen/table.py
queryzen/types.py
queryzen-0.0.1.dist-info/METADATA
queryzen-0.0.1.dist-info/WHEEL
queryzen-0.0.1.dist-info/RECORD
