Metadata-Version: 2.4
Name: queryzen
Version: 0.0.1
Author-email: surister <surister98@gmail.com>
License-Expression: MIT
Requires-Python: ~=3.12
Requires-Dist: httpx<0.29,>=0.28.1
